{
  "preRequisites:9": {
    "0:10": {
      "questIDHigh:4": 0,
      "questIDLow:4": 64
    }
  },
  "properties:10": {
    "betterquesting:10": {
      "autoClaim:1": 0,
      "desc:8": "The §3Coker Unit§r is a machine that turns oil products into §6Petroleum Coke§r, which is the same to the other kinds of coke, aswell as additional fluids as byproducts. The coker unit will require an external heat source in order to function, similar to the §3Crucible§r.\n\n§2§r§2Alongside the §2§r§2§r§2Electric Arc Furnace, the coker unit is one of the most polluting machines of the mod. It spreads 20 soot per second, making it a dangerous machine to use next to a glyphid nest.",
      "globalShare:1": 0,
      "icon:10": {
        "Count:3": 1,
        "Damage:2": 0,
        "OreDict:8": "",
        "id:8": "hbm:tile.machine_coker"
      },
      "isMain:1": 1,
      "isSilent:1": 0,
      "lockedProgress:1": 0,
      "name:8": "Coker Unit",
      "questLogic:8": "AND",
      "repeatTime:3": -1,
      "repeat_relative:1": 1,
      "simultaneous:1": 0,
      "snd_complete:8": "random.levelup",
      "snd_update:8": "random.levelup",
      "taskLogic:8": "AND",
      "visibility:8": "NORMAL"
    }
  },
  "questIDHigh:4": 0,
  "questIDLow:4": 69,
  "rewards:9": {
    "0:10": {
      "ignoreDisabled:1": 0,
      "index:3": 0,
      "rewardID:8": "bq_standard:item",
      "rewards:9": {
        "0:10": {
          "Count:3": 1,
          "Damage:2": 2,
          "OreDict:8": "",
          "id:8": "enhancedlootbags:lootbag"
        }
      }
    }
  },
  "tasks:9": {
    "0:10": {
      "autoConsume:1": 0,
      "consume:1": 0,
      "groupDetect:1": 0,
      "ignoreNBT:1": 0,
      "index:3": 0,
      "partialMatch:1": 1,
      "requiredItems:9": {
        "0:10": {
          "Count:3": 1,
          "Damage:2": 0,
          "OreDict:8": "",
          "id:8": "hbm:tile.machine_coker"
        }
      },
      "taskID:8": "bq_standard:retrieval"
    }
  }
}