{
  "preRequisites:9": {
    "0:10": {
      "questIDHigh:4": 2454242965352891519,
      "questIDLow:4": -6069586783761234700
    }
  },
  "properties:10": {
    "betterquesting:10": {
      "autoClaim:1": 0,
      "desc:8": "§3P2P ME§r can be used to transport massive amounts of channels without laying many cables.\n\n§2This quest serves as a guide on how to effectively use P2P ME.§r\n\nOnce an §3Energy Acceptor§r has been set up, it is highly recommended (and likely needed) that an §3Energy Cell§r is placed next to it as to ensure that there is enough power going to the system, as more components increase the energy demands of the ME system.\n\nAfter that, 2 §3ME Controllers§r are required, one to provide the channels that machines will use, and another to transport the other\u0027s channels by the P2P connections. The top controller can be made bigger by attaching more controllers next to it.\n\n[img height\u003d1000]betterquesting:textures/QB_Controller1.png[/img]\n\nAfter the controllers are placed, on the top controller, a P2P Tunnel - ME needs to be placed on any side. The §9Blue Cable§r will serve as the cable that connects the P2P connections, and as such, it needs to be connected to the bottom controller.\n\n[img height\u003d1000]betterquesting:textures/QB_Controller2.png[/img]\n\nBy linking the P2P connections together using a §6Memory Card§r, the 32 channels from one side of the top controller will only use 1 channel from the bottom controller to be transported to any destination. The §cRed Cable§r now has access to 32 channels.\n\n[img height\u003d1000]betterquesting:textures/QB_Controller3.png[/img]\n\n[img height\u003d1000]betterquesting:textures/QB_Controller4.png[/img]\n\nBy expanding on the previous example, more connections can be added to fully utilize all channels.\n\n[img height\u003d1000]betterquesting:textures/QB_Controller5.png[/img]\n\n[img height\u003d1000]betterquesting:textures/QB_controller6.png[/img]\n",
      "globalShare:1": 0,
      "icon:10": {
        "Count:3": 1,
        "Damage:2": 2,
        "OreDict:8": "",
        "id:8": "chisel:futura"
      },
      "isMain:1": 1,
      "isSilent:1": 0,
      "lockedProgress:1": 0,
      "name:8": "P2P ME Networking",
      "questLogic:8": "AND",
      "repeatTime:3": -1,
      "repeat_relative:1": 1,
      "simultaneous:1": 0,
      "snd_complete:8": "random.levelup",
      "snd_update:8": "random.levelup",
      "taskLogic:8": "AND",
      "visibility:8": "NORMAL"
    }
  },
  "questIDHigh:4": -3048538136168087485,
  "questIDLow:4": -5750375353169774642,
  "rewards:9": {},
  "tasks:9": {
    "0:10": {
      "index:3": 0,
      "taskID:8": "bq_standard:checkbox"
    }
  }
}